{
  "utilization": {
    "triage": {
      "average_utilization_pct": 98.5106866757617,
      "peak_utilization_pct": 100.0,
      "min_utilization_pct": 0.0,
      "current_utilization_pct": 100.0,
      "utilization_std_dev": 9.871598700558062
    },
    "bed": {
      "average_utilization_pct": 8.015006821282402,
      "peak_utilization_pct": 25.0,
      "min_utilization_pct": 0.0,
      "current_utilization_pct": 12.5,
      "utilization_std_dev": 7.7482194341461845
    },
    "nurse": {
      "average_utilization_pct": 98.5106866757617,
      "peak_utilization_pct": 100.0,
      "min_utilization_pct": 0.0,
      "current_utilization_pct": 100.0,
      "utilization_std_dev": 9.871598700558062
    },
    "doctor": {
      "average_utilization_pct": 2.361869031377899,
      "peak_utilization_pct": 25.0,
      "min_utilization_pct": 0.0,
      "current_utilization_pct": 0.0,
      "utilization_std_dev": 7.31220216234928
    }
  },
  "queues": {
    "triage": {
      "average_queue_length": 24.86869031377899,
      "peak_queue_length": 41,
      "min_queue_length": 0,
      "queue_length_std_dev": 9.971385489048943,
      "time_with_queue": 96.418826739427
    },
    "bed": {
      "average_queue_length": 0.0,
      "peak_queue_length": 0,
      "min_queue_length": 0,
      "queue_length_std_dev": 0.0,
      "time_with_queue": 0.0
    },
    "nurse": {
      "average_queue_length": 24.86869031377899,
      "peak_queue_length": 41,
      "min_queue_length": 0,
      "queue_length_std_dev": 9.971385489048943,
      "time_with_queue": 96.418826739427
    },
    "doctor": {
      "average_queue_length": 0.0,
      "peak_queue_length": 0,
      "min_queue_length": 0,
      "queue_length_std_dev": 0.0,
      "time_with_queue": 0.0
    }
  },
  "throughput": {},
  "wait_times": {
    "triage": {
      "average_wait_time_minutes": 40.68008273225106,
      "max_wait_time_minutes": 69.41163062615198,
      "min_wait_time_minutes": 2.1415811694580746,
      "wait_time_std_dev": 17.108812914362613,
      "95th_percentile_wait_time": 63.92114189047743,
      "total_wait_events": 264
    }
  },
  "service_times": {
    "triage": {
      "average_service_time_minutes": 5.017373673938588,
      "max_service_time_minutes": 14.705467271148093,
      "min_service_time_minutes": 3.001270834832244,
      "service_time_std_dev": 1.714377506597825,
      "95th_percentile_service_time": 8.413277371725401,
      "total_service_events": 277
    },
    "doctor": {
      "average_service_time_minutes": 24.85809691986269,
      "max_service_time_minutes": 49.70573760708059,
      "min_service_time_minutes": 10.517666305737295,
      "service_time_std_dev": 7.458648108935759,
      "95th_percentile_service_time": 39.428245168342904,
      "total_service_events": 264
    }
  },
  "system_performance": {
    "simulation_duration_minutes": 0,
    "total_snapshots": 2932,
    "average_system_queue_length": 49.73738062755798,
    "peak_system_queue_length": "82",
    "system_congestion_pct": 96.418826739427,
    "average_system_utilization_pct": 51.84956230104593,
    "peak_system_utilization_pct": 62.5,
    "final_entities_processed": 238,
    "processing_rate_per_hour": 0
  },
  "monitoring_points": 2932,
  "total_resource_events": 1681,
  "service_name": "OperationMetrics",
  "total_records": 0,
  "active_records": 2593,
  "total_duration_minutes": 0,
  "start_time": 0.08583198657796587,
  "end_time": null,
  "counters": {
    "total_records": 4613
  }
}